ai_lab_fat/__init__.py
ai_lab_fat/test.py
ai_lab_fat-4.0.1.dist-info/METADATA
ai_lab_fat-4.0.1.dist-info/WHEEL
ai_lab_fat-4.0.1.dist-info/top_level.txt
ai_lab_fat-4.0.1.dist-info/RECORD
